pypackage/__init__.py
pypackage/admin.py
pypackage/apps.py
pypackage/models.py
pypackage/tests.py
pypackage/urls.py
pypackage/views.py
pypackage/migrations/0001_initial.py
pypackage/migrations/0002_version_archive_format.py
pypackage/migrations/0003_auto_20190524_2305.py
pypackage/migrations/0004_auto_20190525_0032.py
pypackage/migrations/0005_auto_20190525_0037.py
pypackage/migrations/0006_package_owner.py
pypackage/migrations/__init__.py
django_pypackage-0.0.4.dist-info/METADATA
django_pypackage-0.0.4.dist-info/WHEEL
django_pypackage-0.0.4.dist-info/top_level.txt
django_pypackage-0.0.4.dist-info/RECORD
